{
  "sentences": [
    {
      "text": {
        "content": "one economy ticket from SFO to JFK, leaving in a fortnight",
        "beginOffset": 0
      }
    }
  ],
  "tokens": [
    {
      "text": {
        "content": "one",
        "beginOffset": 0
      },
      "partOfSpeech": {
        "tag": "NUM"
      },
      "dependencyEdge": {
        "headTokenIndex": 2,
        "label": "NUM"
      },
      "lemma": "one"
    },
    {
      "text": {
        "content": "economy",
        "beginOffset": 4
      },
      "partOfSpeech": {
        "tag": "NOUN"
      },
      "dependencyEdge": {
        "headTokenIndex": 2,
        "label": "NN"
      },
      "lemma": "economy"
    },
    {
      "text": {
        "content": "ticket",
        "beginOffset": 12
      },
      "partOfSpeech": {
        "tag": "NOUN"
      },
      "dependencyEdge": {
        "headTokenIndex": 2,
        "label": "ROOT"
      },
      "lemma": "ticket"
    },
    {
      "text": {
        "content": "from",
        "beginOffset": 19
      },
      "partOfSpeech": {
        "tag": "ADP"
      },
      "dependencyEdge": {
        "headTokenIndex": 2,
        "label": "PREP"
      },
      "lemma": "from"
    },
    {
      "text": {
        "content": "SFO",
        "beginOffset": 24
      },
      "partOfSpeech": {
        "tag": "NOUN"
      },
      "dependencyEdge": {
        "headTokenIndex": 3,
        "label": "POBJ"
      },
      "lemma": "SFO"
    },
    {
      "text": {
        "content": "to",
        "beginOffset": 28
      },
      "partOfSpeech": {
        "tag": "ADP"
      },
      "dependencyEdge": {
        "headTokenIndex": 2,
        "label": "PREP"
      },
      "lemma": "to"
    },
    {
      "text": {
        "content": "JFK",
        "beginOffset": 31
      },
      "partOfSpeech": {
        "tag": "NOUN"
      },
      "dependencyEdge": {
        "headTokenIndex": 5,
        "label": "POBJ"
      },
      "lemma": "JFK"
    },
    {
      "text": {
        "content": ",",
        "beginOffset": 34
      },
      "partOfSpeech": {
        "tag": "PUNCT"
      },
      "dependencyEdge": {
        "headTokenIndex": 2,
        "label": "P"
      },
      "lemma": ","
    },
    {
      "text": {
        "content": "leaving",
        "beginOffset": 36
      },
      "partOfSpeech": {
        "tag": "VERB"
      },
      "dependencyEdge": {
        "headTokenIndex": 2,
        "label": "VMOD"
      },
      "lemma": "leave"
    },
    {
      "text": {
        "content": "in",
        "beginOffset": 44
      },
      "partOfSpeech": {
        "tag": "ADP"
      },
      "dependencyEdge": {
        "headTokenIndex": 8,
        "label": "PREP"
      },
      "lemma": "in"
    },
    {
      "text": {
        "content": "a",
        "beginOffset": 47
      },
      "partOfSpeech": {
        "tag": "DET"
      },
      "dependencyEdge": {
        "headTokenIndex": 11,
        "label": "DET"
      },
      "lemma": "a"
    },
    {
      "text": {
        "content": "fortnight",
        "beginOffset": 49
      },
      "partOfSpeech": {
        "tag": "NOUN"
      },
      "dependencyEdge": {
        "headTokenIndex": 9,
        "label": "POBJ"
      },
      "lemma": "fortnight"
    }
  ],
  "entities": [
    {
      "name": "SFO",
      "type": "ORGANIZATION",
      "metadata": {
        "wikipedia_url": "http://en.wikipedia.org/wiki/San_Francisco_International_Airport"
      },
      "salience": 0.19722985,
      "mentions": [
        {
          "text": {
            "content": "SFO",
            "beginOffset": 24
          }
        }
      ]
    },
    {
      "name": "JFK",
      "type": "LOCATION",
      "metadata": {
        "wikipedia_url": "http://en.wikipedia.org/wiki/John_F._Kennedy_International_Airport"
      },
      "salience": 0.18761754,
      "mentions": [
        {
          "text": {
            "content": "JFK",
            "beginOffset": 31
          }
        }
      ]
    }
  ],
  "language": "en"
}
