{
  "sentences": [
    {
      "text": {
        "content": "A 10-day trip from LA to New York ending 2nd of September for 3",
        "beginOffset": 0
      }
    }
  ],
  "tokens": [
    {
      "text": {
        "content": "A",
        "beginOffset": 0
      },
      "partOfSpeech": {
        "tag": "DET"
      },
      "dependencyEdge": {
        "headTokenIndex": 4,
        "label": "DET"
      },
      "lemma": "A"
    },
    {
      "text": {
        "content": "10",
        "beginOffset": 2
      },
      "partOfSpeech": {
        "tag": "NUM"
      },
      "dependencyEdge": {
        "headTokenIndex": 3,
        "label": "NUM"
      },
      "lemma": "10"
    },
    {
      "text": {
        "content": "-",
        "beginOffset": 4
      },
      "partOfSpeech": {
        "tag": "PUNCT"
      },
      "dependencyEdge": {
        "headTokenIndex": 3,
        "label": "P"
      },
      "lemma": "-"
    },
    {
      "text": {
        "content": "day",
        "beginOffset": 5
      },
      "partOfSpeech": {
        "tag": "NOUN"
      },
      "dependencyEdge": {
        "headTokenIndex": 4,
        "label": "NN"
      },
      "lemma": "day"
    },
    {
      "text": {
        "content": "trip",
        "beginOffset": 9
      },
      "partOfSpeech": {
        "tag": "NOUN"
      },
      "dependencyEdge": {
        "headTokenIndex": 4,
        "label": "ROOT"
      },
      "lemma": "trip"
    },
    {
      "text": {
        "content": "from",
        "beginOffset": 14
      },
      "partOfSpeech": {
        "tag": "ADP"
      },
      "dependencyEdge": {
        "headTokenIndex": 4,
        "label": "PREP"
      },
      "lemma": "from"
    },
    {
      "text": {
        "content": "LA",
        "beginOffset": 19
      },
      "partOfSpeech": {
        "tag": "NOUN"
      },
      "dependencyEdge": {
        "headTokenIndex": 5,
        "label": "POBJ"
      },
      "lemma": "LA"
    },
    {
      "text": {
        "content": "to",
        "beginOffset": 22
      },
      "partOfSpeech": {
        "tag": "ADP"
      },
      "dependencyEdge": {
        "headTokenIndex": 4,
        "label": "PREP"
      },
      "lemma": "to"
    },
    {
      "text": {
        "content": "New",
        "beginOffset": 25
      },
      "partOfSpeech": {
        "tag": "NOUN"
      },
      "dependencyEdge": {
        "headTokenIndex": 9,
        "label": "NN"
      },
      "lemma": "New"
    },
    {
      "text": {
        "content": "York",
        "beginOffset": 29
      },
      "partOfSpeech": {
        "tag": "NOUN"
      },
      "dependencyEdge": {
        "headTokenIndex": 7,
        "label": "POBJ"
      },
      "lemma": "York"
    },
    {
      "text": {
        "content": "ending",
        "beginOffset": 34
      },
      "partOfSpeech": {
        "tag": "VERB"
      },
      "dependencyEdge": {
        "headTokenIndex": 4,
        "label": "VMOD"
      },
      "lemma": "end"
    },
    {
      "text": {
        "content": "2nd",
        "beginOffset": 41
      },
      "partOfSpeech": {
        "tag": "NOUN"
      },
      "dependencyEdge": {
        "headTokenIndex": 10,
        "label": "DOBJ"
      },
      "lemma": "2nd"
    },
    {
      "text": {
        "content": "of",
        "beginOffset": 45
      },
      "partOfSpeech": {
        "tag": "ADP"
      },
      "dependencyEdge": {
        "headTokenIndex": 11,
        "label": "PREP"
      },
      "lemma": "of"
    },
    {
      "text": {
        "content": "September",
        "beginOffset": 48
      },
      "partOfSpeech": {
        "tag": "NOUN"
      },
      "dependencyEdge": {
        "headTokenIndex": 12,
        "label": "POBJ"
      },
      "lemma": "September"
    },
    {
      "text": {
        "content": "for",
        "beginOffset": 58
      },
      "partOfSpeech": {
        "tag": "ADP"
      },
      "dependencyEdge": {
        "headTokenIndex": 10,
        "label": "PREP"
      },
      "lemma": "for"
    },
    {
      "text": {
        "content": "3",
        "beginOffset": 62
      },
      "partOfSpeech": {
        "tag": "NUM"
      },
      "dependencyEdge": {
        "headTokenIndex": 14,
        "label": "POBJ"
      },
      "lemma": "3"
    }
  ],
  "entities": [
    {
      "name": "LA",
      "type": "LOCATION",
      "metadata": {
        "wikipedia_url": "http://en.wikipedia.org/wiki/Los_Angeles"
      },
      "salience": 0.25751841,
      "mentions": [
        {
          "text": {
            "content": "LA",
            "beginOffset": 19
          }
        }
      ]
    },
    {
      "name": "New York",
      "type": "LOCATION",
      "metadata": {
        "wikipedia_url": "http://en.wikipedia.org/wiki/New_York_City"
      },
      "salience": 0.20622244,
      "mentions": [
        {
          "text": {
            "content": "New York",
            "beginOffset": 25
          }
        }
      ]
    }
  ],
  "language": "en"
}
